{"nodes": [{"id": "nemotron3nano_test", "label": "nemotron3nano_test.go", "file_type": "code", "source_file": "model\\renderers\\nemotron3nano_test.go", "source_location": "L1"}, {"id": "nemotron3nano_test_testnemotron3nanorenderer", "label": "TestNemotron3NanoRenderer()", "file_type": "code", "source_file": "model\\renderers\\nemotron3nano_test.go", "source_location": "L11"}], "edges": [{"source": "nemotron3nano_test", "target": "testing", "relation": "imports_from", "confidence": "EXTRACTED", "source_file": "model\\renderers\\nemotron3nano_test.go", "source_location": "L4", "weight": 1.0}, {"source": "nemotron3nano_test", "target": "cmp", "relation": "imports_from", "confidence": "EXTRACTED", "source_file": "model\\renderers\\nemotron3nano_test.go", "source_location": "L6", "weight": 1.0}, {"source": "nemotron3nano_test", "target": "api", "relation": "imports_from", "confidence": "EXTRACTED", "source_file": "model\\renderers\\nemotron3nano_test.go", "source_location": "L8", "weight": 1.0}, {"source": "nemotron3nano_test", "target": "nemotron3nano_test_testnemotron3nanorenderer", "relation": "contains", "confidence": "EXTRACTED", "source_file": "model\\renderers\\nemotron3nano_test.go", "source_location": "L11", "weight": 1.0}]}